fxbaogao_mcp/__init__.py
fxbaogao_mcp/__main__.py
fxbaogao_mcp/server.py
fxbaogao_mcp-0.1.4.dist-info/METADATA
fxbaogao_mcp-0.1.4.dist-info/WHEEL
fxbaogao_mcp-0.1.4.dist-info/entry_points.txt
fxbaogao_mcp-0.1.4.dist-info/RECORD
