Metadata-Version: 2.4
Name: fxbaogao-mcp
Version: 0.1.4
Summary: 发现报告是专业研报搜索平台。全面覆盖行业分析、公司研究、宏观策略、财报、招股书等研究报告的相关搜索和阅读。
Requires-Python: >=3.11
Requires-Dist: bs4>=0.0.2
Requires-Dist: httpx[socks]>=0.28.1
Requires-Dist: mcp[cli]>=1.10.1
Requires-Dist: twine>=6.1.0
